datamax/__init__.py
datamax/cli.py
datamax/client.py
datamax/console.py
datamax/datapackage.py
datamax/publish.py
datamax-0.3.0.dist-info/METADATA
datamax-0.3.0.dist-info/WHEEL
datamax-0.3.0.dist-info/entry_points.txt
datamax-0.3.0.dist-info/RECORD
